supavisor/__init__.py
supavisor/client.py
supavisor/types.py
supavisor-0.1.0.dist-info/METADATA
supavisor-0.1.0.dist-info/WHEEL
supavisor-0.1.0.dist-info/RECORD
