Metadata-Version: 2.1
Name: supavisor
Version: 0.1.0
Summary: A simple library for interacting with a Supavisor Instance
Home-page: https://github.com/jsaied99/supavisor
License: MIT
Author: Jamal Saied
Author-email: jsaied99@gmail.com
Requires-Python: >=3.11,<4.0
Classifier: License :: OSI Approved :: MIT License
Classifier: Programming Language :: Python :: 3
Classifier: Programming Language :: Python :: 3.11
Classifier: Programming Language :: Python :: 3.12
Requires-Dist: aiohttp (>=3.9.5,<4.0.0)
Requires-Dist: orjson (>=3.10.6,<4.0.0)
Requires-Dist: pydantic (>=2.8.2,<3.0.0)
Project-URL: Repository, https://github.com/jsaied99/supavisor
